openmm_systems/__init__.py
openmm_systems/_version.py
openmm_systems/constants.py
openmm_systems/data/T4-lysozyme-L99A-implicit/complex-min.sander.out
openmm_systems/data/T4-lysozyme-L99A-implicit/complex-minimized.crd
openmm_systems/data/T4-lysozyme-L99A-implicit/complex-testenergy.sander.out
openmm_systems/data/T4-lysozyme-L99A-implicit/complex.crd
openmm_systems/data/T4-lysozyme-L99A-implicit/complex.pdb
openmm_systems/data/T4-lysozyme-L99A-implicit/complex.prmtop
openmm_systems/data/T4-lysozyme-L99A-implicit/leap.log
openmm_systems/data/T4-lysozyme-L99A-implicit/ligand-min.sander.out
openmm_systems/data/T4-lysozyme-L99A-implicit/ligand-minimized.crd
openmm_systems/data/T4-lysozyme-L99A-implicit/ligand-testenergy.sander.out
openmm_systems/data/T4-lysozyme-L99A-implicit/ligand.crd
openmm_systems/data/T4-lysozyme-L99A-implicit/ligand.frcmod
openmm_systems/data/T4-lysozyme-L99A-implicit/ligand.mol2
openmm_systems/data/T4-lysozyme-L99A-implicit/ligand.pdb
openmm_systems/data/T4-lysozyme-L99A-implicit/ligand.prmtop
openmm_systems/data/T4-lysozyme-L99A-implicit/ligand.tripos.mol2
openmm_systems/data/T4-lysozyme-L99A-implicit/mdinfo
openmm_systems/data/T4-lysozyme-L99A-implicit/min.sander.in
openmm_systems/data/T4-lysozyme-L99A-implicit/receptor-min.sander.out
openmm_systems/data/T4-lysozyme-L99A-implicit/receptor-minimized.crd
openmm_systems/data/T4-lysozyme-L99A-implicit/receptor-testenergy.sander.out
openmm_systems/data/T4-lysozyme-L99A-implicit/receptor.crd
openmm_systems/data/T4-lysozyme-L99A-implicit/receptor.pdb
openmm_systems/data/T4-lysozyme-L99A-implicit/receptor.prmtop
openmm_systems/data/T4-lysozyme-L99A-implicit/setup.leap.in
openmm_systems/data/T4-lysozyme-L99A-implicit/setup.leap.out
openmm_systems/data/T4-lysozyme-L99A-implicit/testenergy.sander.in
openmm_systems/data/alanine-dipeptide-explicit/alanine-dipeptide.crd
openmm_systems/data/alanine-dipeptide-explicit/alanine-dipeptide.pdb
openmm_systems-0.0.0.dist-info/AUTHORS.org
openmm_systems-0.0.0.dist-info/LICENSE
openmm_systems-0.0.0.dist-info/METADATA
openmm_systems-0.0.0.dist-info/WHEEL
openmm_systems-0.0.0.dist-info/entry_points.txt
openmm_systems-0.0.0.dist-info/top_level.txt
openmm_systems-0.0.0.dist-info/RECORD
